dbutils/__init__.py
dbutils/dbutils.py
dbutils3/__init__.py
dbutils3/dbutils.py
dbutils3_gonzalo123-3.0.2.dist-info/LICENSE
dbutils3_gonzalo123-3.0.2.dist-info/METADATA
dbutils3_gonzalo123-3.0.2.dist-info/WHEEL
dbutils3_gonzalo123-3.0.2.dist-info/top_level.txt
dbutils3_gonzalo123-3.0.2.dist-info/RECORD
