Metadata-Version: 2.1
Name: dbutils3-gonzalo123
Version: 3.0.2
Summary: psycopg3 db utils
Home-page: https://github.com/gonzalo123/dbutils3
Author: Gonzalo Ayuso
Author-email: gonzalo123@gmail.com
License: MIT
Keywords: psycopg3
Platform: UNKNOWN
Classifier: Programming Language :: Python :: 3
Classifier: License :: OSI Approved :: MIT License
Classifier: Operating System :: OS Independent
Requires-Python: >=3.5
License-File: LICENSE
Requires-Dist: psycopg >=3
